<?xml version="1.0" encoding="UTF-8"?>
<objects serializationModel="Studio.02.02.00">
	<object class="AudioFile" id="{ccb3e267-c13e-4b76-9b6b-9ee036988b75}">
		<property name="assetPath">
			<value>SFX/SFX-DRON_Dash-OS.wav</value>
		</property>
		<property name="frequencyInKHz">
			<value>48</value>
		</property>
		<property name="channelCount">
			<value>1</value>
		</property>
		<property name="length">
			<value>0.99502083333333335</value>
		</property>
		<relationship name="masterAssetFolder">
			<destination>{53e06c3e-7bce-4f4f-b10d-fb04dc4ebf1a}</destination>
		</relationship>
	</object>
</objects>
